fetchio/__init__.py
fetchio/http.py
tests/__init__.py
tests/test_http.py
fetchio-1.0.0.dist-info/LICENSE
fetchio-1.0.0.dist-info/METADATA
fetchio-1.0.0.dist-info/WHEEL
fetchio-1.0.0.dist-info/top_level.txt
fetchio-1.0.0.dist-info/RECORD
