Metadata-Version: 2.1
Name: fetchio
Version: 1.0.0
Summary: A simple HTTP library in Python similar to JavaScript fetch.
Home-page: https://github.com/tal7aouy/fetchio
Author: Mhammed Talhaouy
Author-email: tal7apuy@gmail.com
Classifier: Programming Language :: Python :: 3
Classifier: License :: OSI Approved :: MIT License
Classifier: Operating System :: OS Independent
Requires-Python: >=3.10
License-File: LICENSE
Requires-Dist: requests
